glchat_plugin/__init__.py
glchat_plugin/config/__init__.py
glchat_plugin/config/app_config.py
glchat_plugin/config/constant.py
glchat_plugin/context/__init__.py
glchat_plugin/context/context_manager.py
glchat_plugin/handler/__init__.py
glchat_plugin/handler/base_post_login_handler.py
glchat_plugin/pipeline/__init__.py
glchat_plugin/pipeline/base_pipeline_preset_config.py
glchat_plugin/pipeline/pipeline_handler.py
glchat_plugin/pipeline/pipeline_plugin.py
glchat_plugin/pipeline/tool_processor.py
glchat_plugin/service/__init__.py
glchat_plugin/service/base_rate_limiter_service.py
glchat_plugin/service/base_tenant_service.py
glchat_plugin/service/base_user_service.py
glchat_plugin/storage/__init__.py
glchat_plugin/storage/base_anonymizer_storage.py
glchat_plugin/storage/base_chat_history_storage.py
glchat_plugin/tools/__init__.py
glchat_plugin/tools/decorators.py
glchat_plugin-0.4.8.dist-info/METADATA
glchat_plugin-0.4.8.dist-info/WHEEL
glchat_plugin-0.4.8.dist-info/top_level.txt
glchat_plugin-0.4.8.dist-info/RECORD
