Metadata-Version: 2.4
Name: glchat-plugin
Version: 0.4.8
Author-email: GenAI SDK Team <gat-sdk@gdplabs.id>
Requires-Python: <3.13,>=3.11
Requires-Dist: poetry>=2.1.3
Requires-Dist: bosa-core-binary>=0.8.6
Requires-Dist: gllm-core-binary>=0.3.0
Requires-Dist: gllm-inference-binary>=0.5.0
Requires-Dist: gllm-pipeline-binary>=0.4.0
Requires-Dist: langchain>=0.3.0
Requires-Dist: langchain-core>=0.3.0
Requires-Dist: semver>=3.0.4
Provides-Extra: flair
Requires-Dist: flair; extra == "flair"
Provides-Extra: dev
Requires-Dist: coverage>=7.4.4; extra == "dev"
Requires-Dist: mypy>=1.15.0; extra == "dev"
Requires-Dist: pre-commit>=3.7.0; extra == "dev"
Requires-Dist: pytest>=8.1.1; extra == "dev"
Requires-Dist: pytest-asyncio>=0.23.6; extra == "dev"
Requires-Dist: pytest-cov>=5.0.0; extra == "dev"
Requires-Dist: ruff>=0.6.7; extra == "dev"
